khutils/__init__.py
khutils/dates.py
khutils/numbers.py
khutils-1.0.3.dist-info/METADATA
khutils-1.0.3.dist-info/WHEEL
khutils-1.0.3.dist-info/top_level.txt
khutils-1.0.3.dist-info/RECORD
