Metadata-Version: 2.4
Name: khutils
Version: 1.0.3
Summary: Utilities for converting numbers, dates, and text to/from Khmer
Author-email: Chorn Penghong <chorn.penghong168@gmail.com>
License: MIT
Keywords: khmer,khmer number,khmer date,khmer text
Classifier: Programming Language :: Python :: 3
Classifier: License :: OSI Approved :: MIT License
Classifier: Operating System :: OS Independent
